Diconfig/__init__.py
Diconfig/diconfig.py
diconfig-0.1.1.dist-info/LICENSE
diconfig-0.1.1.dist-info/METADATA
diconfig-0.1.1.dist-info/WHEEL
diconfig-0.1.1.dist-info/RECORD
